AUTHORS
COPYING
HACKING
MANIFEST.in
Makefile
NEWS
README
RELEASE
TODO
setup.py
include/_pedmodule.h
include/convert.h
include/exceptions.h
include/pyconstraint.h
include/pydevice.h
include/pydisk.h
include/pyfilesys.h
include/pygeom.h
include/pynatmath.h
include/pytimer.h
include/pyunit.h
include/docstrings/pyconstraint.h
include/docstrings/pydevice.h
include/docstrings/pydisk.h
include/docstrings/pyfilesys.h
include/docstrings/pygeom.h
include/docstrings/pynatmath.h
include/typeobjects/pyconstraint.h
include/typeobjects/pydevice.h
include/typeobjects/pydisk.h
include/typeobjects/pyfilesys.h
include/typeobjects/pygeom.h
include/typeobjects/pynatmath.h
include/typeobjects/pytimer.h
pyparted.egg-info/PKG-INFO
pyparted.egg-info/SOURCES.txt
pyparted.egg-info/dependency_links.txt
pyparted.egg-info/top_level.txt
src/_pedmodule.c
src/convert.c
src/pyconstraint.c
src/pydevice.c
src/pydisk.c
src/pyfilesys.c
src/pygeom.c
src/pynatmath.c
src/pytimer.c
src/pyunit.c
src/parted/__init__.py
src/parted/alignment.py
src/parted/cachedlist.py
src/parted/constraint.py
src/parted/decorators.py
src/parted/device.py
src/parted/disk.py
src/parted/filesystem.py
src/parted/geometry.py
src/parted/partition.py
tests/__init__.py
tests/baseclass.py
tests/test__ped_alignment.py
tests/test__ped_chsgeometry.py
tests/test__ped_constraint.py
tests/test__ped_device.py
tests/test__ped_disk.py
tests/test__ped_disktype.py
tests/test__ped_filesystem.py
tests/test__ped_filesystemtype.py
tests/test__ped_geometry.py
tests/test__ped_partition.py
tests/test__ped_ped.py
tests/test_parted_alignment.py
tests/test_parted_constraint.py
tests/test_parted_device.py
tests/test_parted_disk.py
tests/test_parted_filesystem.py
tests/test_parted_geometry.py
tests/test_parted_parted.py
tests/test_parted_partition.py
tests/pylint/runpylint.py