Metadata-Version: 2.1
Name: pyparted
Version: 3.12.0
Summary: Python bindings for GNU parted
Home-page: https://github.com/dcantrell/pyparted/
Author: David Cantrell
Author-email: dcantrell@redhat.com
License: GPLv2+
Platform: UNKNOWN
License-File: COPYING
License-File: AUTHORS
